dggrid4py/__init__.py
dggrid4py/auxlat.py
dggrid4py/dggrid_runner.py
dggrid4py/igeo7.py
dggrid4py/igeo7_ext.py
dggrid4py/interrupt.py
dggrid4py/tool.py
dggrid4py-0.5.3.dist-info/METADATA
dggrid4py-0.5.3.dist-info/WHEEL
dggrid4py-0.5.3.dist-info/licenses/LICENSE
dggrid4py-0.5.3.dist-info/RECORD
