Metadata-Version: 2.4
Name: dggrid4py
Version: 0.5.3
Summary: a Python library to run highlevel functions of DGGRIDv7 and v8
License-Expression: AGPL-3.0-or-later
License-File: LICENSE
Keywords: python,GIS,DGGS,DGGRID,hexagons,grids,spatial statistics,IGEO7
Author: Alexander Kmoch
Author-email: alexander.kmoch@ut.ee
Requires-Python: >=3.10, <4.0.0
Classifier: Development Status :: 5 - Production/Stable
Classifier: Environment :: Console
Classifier: Intended Audience :: Education
Classifier: Intended Audience :: Science/Research
Classifier: License :: OSI Approved :: GNU Affero General Public License v3 or later (AGPLv3+)
Classifier: Programming Language :: Python :: 3
Classifier: Operating System :: MacOS :: MacOS X
Classifier: Operating System :: POSIX
Classifier: Operating System :: Unix
Classifier: Operating System :: POSIX :: Linux
Classifier: Topic :: Scientific/Engineering :: GIS
Requires-Dist: fiona (>=1.8.0,<2.0.0)
Requires-Dist: geopandas (>=0.9.0,<2.0.0)
Requires-Dist: numpy (>=1.22.0,<3.0.0)
Requires-Dist: pandas (>=1.4.0,<3.0.0)
Requires-Dist: pygeodesy (>=25.10.10,<26.0.0)
Requires-Dist: pyogrio (>=0.11.1,<0.12.0)
Requires-Dist: shapely (>=1.8.0,<3.0.0)
